covidapi/__init__.py
covidapi-0.1.0.dist-info/LICENSE
covidapi-0.1.0.dist-info/METADATA
covidapi-0.1.0.dist-info/WHEEL
covidapi-0.1.0.dist-info/top_level.txt
covidapi-0.1.0.dist-info/RECORD
